markdown_tables_extended/__init__.py
markdown_tables_extended/_version.py
markdown_tables_extended-0.1.3.dist-info/LICENSE
markdown_tables_extended-0.1.3.dist-info/WHEEL
markdown_tables_extended-0.1.3.dist-info/METADATA
markdown_tables_extended-0.1.3.dist-info/RECORD
