Metadata-Version: 2.1
Name: markdown_tables_extended
Version: 0.1.3
Summary: This is an extended version of the tables extension of Python-Markdown. It contains addtions from the cell_row_span extension and allows to create tables without header.
Keywords: markdown_grid_tables,extension,plugin,markdown,mkdocs
Author-email: Daniel Riggins <danielr.riggins@gmail.com>
Requires-Python: >=3.7
Classifier: Development Status :: 3 - Alpha
Classifier: Intended Audience :: Developers
Classifier: License :: OSI Approved :: BSD License
Classifier: Programming Language :: Python
Classifier: Programming Language :: Python :: 3
Classifier: Topic :: Software Development
Classifier: Topic :: Text Processing :: Markup
Classifier: Topic :: Text Processing :: Markup :: Markdown
Requires-Dist: markdown>=3.0.0
Project-URL: documentation, https://github.com/fumbles/tables_extended
Project-URL: homepage, https://github.com/fumbles/tables_extended
Project-URL: repository, https://github.com/fumbles/tables_extended
